smart_data_science/__init__.py
smart_data_science/analysis/info.py
smart_data_science/analysis/info_advanced.py
smart_data_science/analysis/plot.py
smart_data_science/cloud/gcp.py
smart_data_science/core/io.py
smart_data_science/core/logger.py
smart_data_science/core/samples_data/README.md
smart_data_science/core/samples_data/churn_bank.csv
smart_data_science/core/samples_data/electric_motor_50k.parquet
smart_data_science/core/samples_data/energy_building.parquet
smart_data_science/core/samples_data/supermarket_sales.parquet
smart_data_science/core/samples_data/supply_chain.csv
smart_data_science/core/samples_data_module.py
smart_data_science/core/samples_scenario/scenario_electric_motor.py
smart_data_science/core/samples_scenario/scenario_energy_building.py
smart_data_science/core/samples_scenario/scenario_supermarket_sales.py
smart_data_science/core/samples_scenario/scenario_supply_chain.py
smart_data_science/core/samples_scenario_module.py
smart_data_science/core/scenario_base.py
smart_data_science/core/system.py
smart_data_science/dev/modelling/ml_classifier_old_format/prediction.py
smart_data_science/graph_data/network_graph.py
smart_data_science/llm/assistant.py
smart_data_science/ml/ml_base.py
smart_data_science/ml/ml_classifier.py
smart_data_science/ml/ml_contributions.py
smart_data_science/ml/ml_intervals.py
smart_data_science/ml/ml_regressor.py
smart_data_science/ml/ml_tune.py
smart_data_science/ml/ml_utils.py
smart_data_science/ml/plot_classifier.py
smart_data_science/ml/plot_contributions.py
smart_data_science/ml/plot_general.py
smart_data_science/ml/plot_intervals.py
smart_data_science/ml/plot_regressor.py
smart_data_science/nlp/semantic_search.py
smart_data_science/optimization/sequence.py
smart_data_science/process/clean.py
smart_data_science/process/etl.py
smart_data_science/process/transform.py
smart_data_science/smart_data_science.py
smart_data_science/time_series/date_time.py
smart_data_science/ui/ui_assistant.py
smart_data_science/ui/ui_info.py
smart_data_science-0.1.2.dist-info/LICENSE
smart_data_science-0.1.2.dist-info/WHEEL
smart_data_science-0.1.2.dist-info/METADATA
smart_data_science-0.1.2.dist-info/RECORD
